genkit/codec.py
genkit/py.typed
genkit/testing.py
genkit/ai/__init__.py
genkit/ai/_aio.py
genkit/ai/_base.py
genkit/ai/_base_async.py
genkit/ai/_plugin.py
genkit/ai/_registry.py
genkit/ai/_runtime.py
genkit/ai/_server.py
genkit/aio/__init__.py
genkit/aio/_compat.py
genkit/aio/_util.py
genkit/aio/channel.py
genkit/aio/loop.py
genkit/blocks/__init__.py
genkit/blocks/document.py
genkit/blocks/embedding.py
genkit/blocks/evaluator.py
genkit/blocks/generate.py
genkit/blocks/messages.py
genkit/blocks/middleware.py
genkit/blocks/model.py
genkit/blocks/prompt.py
genkit/blocks/retriever.py
genkit/blocks/tools.py
genkit/blocks/formats/__init__.py
genkit/blocks/formats/json.py
genkit/blocks/formats/types.py
genkit/core/__init__.py
genkit/core/constants.py
genkit/core/context.py
genkit/core/environment.py
genkit/core/error.py
genkit/core/extract.py
genkit/core/flows.py
genkit/core/reflection.py
genkit/core/registry.py
genkit/core/schema.py
genkit/core/status_types.py
genkit/core/tracing.py
genkit/core/typing.py
genkit/core/action/__init__.py
genkit/core/action/_action.py
genkit/core/action/_key.py
genkit/core/action/_tracing.py
genkit/core/action/_util.py
genkit/core/action/types.py
genkit/core/trace/__init__.py
genkit/core/trace/default_exporter.py
genkit/core/trace/types.py
genkit/lang/__init__.py
genkit/lang/deprecations.py
genkit/plugins/.gitignore
genkit/types/__init__.py
genkit/web/__init__.py
genkit/web/requests.py
genkit/web/typing.py
genkit/web/manager/__init__.py
genkit/web/manager/_adapters.py
genkit/web/manager/_base_server.py
genkit/web/manager/_info.py
genkit/web/manager/_manager.py
genkit/web/manager/_ports.py
genkit/web/manager/_server.py
genkit/web/manager/signals.py
genkit-0.3.2.dist-info/METADATA
genkit-0.3.2.dist-info/WHEEL
genkit-0.3.2.dist-info/licenses/LICENSE
genkit-0.3.2.dist-info/RECORD
